isbnlib_dnb/__init__.py
isbnlib_dnb/_dnb.py
isbnlib_dnb-0.0.4.dist-info/LICENSE-LGPL.txt
isbnlib_dnb-0.0.4.dist-info/METADATA
isbnlib_dnb-0.0.4.dist-info/WHEEL
isbnlib_dnb-0.0.4.dist-info/entry_points.txt
isbnlib_dnb-0.0.4.dist-info/top_level.txt
isbnlib_dnb-0.0.4.dist-info/RECORD
