Metadata-Version: 2.1
Name: isbnlib-dnb
Version: 0.0.4
Summary: A plugin for isbnlib that pulls metadata from the Deutsche National Bibliothek (Germany)
Home-page: https://github.com/arangb/isbnlib-dnb
Author: arangb
Author-email: arangbellido@gmail.com
License: LGPL v3
Download-URL: https://github.com/arangb/isbnlib-dnb/archive/v0.0.4.zip
Keywords: ISBN isbnlib dnb bibliographic-references
Platform: UNKNOWN
Classifier: Programming Language :: Python
Classifier: Programming Language :: Python :: 2
Classifier: Programming Language :: Python :: 2.7
Classifier: Programming Language :: Python :: 3
Classifier: Programming Language :: Python :: 3.5
Classifier: Programming Language :: Python :: 3.6
Classifier: Programming Language :: Python :: 3.7
Classifier: Programming Language :: Python :: 3.8
Classifier: License :: OSI Approved :: GNU Lesser General Public License v3 (LGPLv3)
Classifier: Operating System :: OS Independent
Classifier: Development Status :: 4 - Beta
Classifier: Intended Audience :: Developers
Classifier: Intended Audience :: End Users/Desktop
Classifier: Environment :: Console
Classifier: Topic :: Text Processing :: General
Classifier: Topic :: Software Development :: Libraries :: Python Modules
Requires-Dist: isbnlib (<3.11.0,>=3.9.3)
